LICENSE
MANIFEST.in
README.md
setup.cfg
setup.py
docassemble/__init__.py
docassemble.LegalHelpforRenters.egg-info/PKG-INFO
docassemble.LegalHelpforRenters.egg-info/SOURCES.txt
docassemble.LegalHelpforRenters.egg-info/dependency_links.txt
docassemble.LegalHelpforRenters.egg-info/namespace_packages.txt
docassemble.LegalHelpforRenters.egg-info/not-zip-safe
docassemble.LegalHelpforRenters.egg-info/top_level.txt
docassemble/LegalHelpforRenters/__init__.py
docassemble/LegalHelpforRenters/data/questions/wrongful_occ_answer.yml
docassemble/LegalHelpforRenters/data/sources/README.md
docassemble/LegalHelpforRenters/data/static/README.md
docassemble/LegalHelpforRenters/data/static/civil_judgment_order_rental.png
docassemble/LegalHelpforRenters/data/static/wrongful_occupation_petition.png
docassemble/LegalHelpforRenters/data/static/wrongful_occupation_summons.png
docassemble/LegalHelpforRenters/data/templates/README.md
docassemble/LegalHelpforRenters/data/templates/wrongful_occupation_answer.pdf