Metadata-Version: 2.1
Name: docassemble.LegalHelpforRenters
Version: 0.0.1
Summary: A docassemble extension.
Home-page: https://docassemble.org
Author: System Administrator
Author-email: dhenry@lawv.net
License: The MIT License (MIT)
Platform: UNKNOWN
License-File: LICENSE
